LICENSE
MANIFEST.in
README.md
setup.py
./.gitlab-ci.yml
./pyPhasesRecordloaderSHHS/config.yaml
./pyPhasesRecordloaderSHHS/configs/shhs.yaml
./pyPhasesRecordloaderSHHS/configs/shhs2.yaml
pyPhasesRecordloaderSHHS/Plugin.py
pyPhasesRecordloaderSHHS/__init__.py
pyPhasesRecordloaderSHHS/config.yaml
pyPhasesRecordloaderSHHS.egg-info/PKG-INFO
pyPhasesRecordloaderSHHS.egg-info/SOURCES.txt
pyPhasesRecordloaderSHHS.egg-info/dependency_links.txt
pyPhasesRecordloaderSHHS.egg-info/requires.txt
pyPhasesRecordloaderSHHS.egg-info/top_level.txt
pyPhasesRecordloaderSHHS/configs/shhs.yaml
pyPhasesRecordloaderSHHS/configs/shhs2.yaml
pyPhasesRecordloaderSHHS/recordLoaders/NSRRAnnotationLoader.py
pyPhasesRecordloaderSHHS/recordLoaders/RecordLoaderSHHS.py
pyPhasesRecordloaderSHHS/recordLoaders/SHHSAnnotationLoader.py
pyPhasesRecordloaderSHHS/recordLoaders/__init__.py